find_tar_pic/__init__.py
find_tar_pic/my_tool.py
ageng_tool-0.0.1.dist-info/METADATA
ageng_tool-0.0.1.dist-info/WHEEL
ageng_tool-0.0.1.dist-info/top_level.txt
ageng_tool-0.0.1.dist-info/RECORD
